{"benchmark":"NASDAQ:QQQ","tracking_since":"2026-07-02","updated":"2026-07-07","horizons":[5,20,60],"groups":[{"name":"Breakouts","signals":230,"stats":{"5":{"n":0,"pending":194,"missing":0,"invalid":0,"pre_tracking":36,"hit_rate":null,"median_excess":null,"mean_excess":null,"mean_raw":null},"20":{"n":0,"pending":194,"missing":0,"invalid":0,"pre_tracking":36,"hit_rate":null,"median_excess":null,"mean_excess":null,"mean_raw":null},"60":{"n":0,"pending":194,"missing":0,"invalid":0,"pre_tracking":36,"hit_rate":null,"median_excess":null,"mean_excess":null,"mean_raw":null}}},{"name":"First-day signals (NEW)","signals":199,"stats":{"5":{"n":0,"pending":163,"missing":0,"invalid":0,"pre_tracking":36,"hit_rate":null,"median_excess":null,"mean_excess":null,"mean_raw":null},"20":{"n":0,"pending":163,"missing":0,"invalid":0,"pre_tracking":36,"hit_rate":null,"median_excess":null,"mean_excess":null,"mean_raw":null},"60":{"n":0,"pending":163,"missing":0,"invalid":0,"pre_tracking":36,"hit_rate":null,"median_excess":null,"mean_excess":null,"mean_raw":null}}},{"name":"Continuation days","signals":31,"stats":{"5":{"n":0,"pending":31,"missing":0,"invalid":0,"pre_tracking":0,"hit_rate":null,"median_excess":null,"mean_excess":null,"mean_raw":null},"20":{"n":0,"pending":31,"missing":0,"invalid":0,"pre_tracking":0,"hit_rate":null,"median_excess":null,"mean_excess":null,"mean_raw":null},"60":{"n":0,"pending":31,"missing":0,"invalid":0,"pre_tracking":0,"hit_rate":null,"median_excess":null,"mean_excess":null,"mean_raw":null}}},{"name":"Old state rule (comparison)","signals":167,"stats":{"5":{"n":0,"pending":131,"missing":0,"invalid":0,"pre_tracking":36,"hit_rate":null,"median_excess":null,"mean_excess":null,"mean_raw":null},"20":{"n":0,"pending":131,"missing":0,"invalid":0,"pre_tracking":36,"hit_rate":null,"median_excess":null,"mean_excess":null,"mean_raw":null},"60":{"n":0,"pending":131,"missing":0,"invalid":0,"pre_tracking":36,"hit_rate":null,"median_excess":null,"mean_excess":null,"mean_raw":null}}}]}